<annotation>
	<folder>data_all</folder>
	<filename>000160.jpg</filename>
	<path>D:\dimension\data_all\000160.jpg</path>
	<source>
		<database>Unknown</database>
	</source>
	<size>
		<width>2560</width>
		<height>1440</height>
		<depth>3</depth>
	</size>
	<segmented>0</segmented>
	<object>
		<name>Head_with_Helmet</name>
		<pose>Unspecified</pose>
		<truncated>0</truncated>
		<difficult>0</difficult>
		<bndbox>
			<xmin>1491</xmin>
			<ymin>775</ymin>
			<xmax>1554</xmax>
			<ymax>825</ymax>
		</bndbox>
	</object>
	<object>
		<name>Head_without_covering</name>
		<pose>Unspecified</pose>
		<truncated>0</truncated>
		<difficult>0</difficult>
		<bndbox>
			<xmin>1430</xmin>
			<ymin>745</ymin>
			<xmax>1500</xmax>
			<ymax>795</ymax>
		</bndbox>
	</object>
	<object>
		<name>Uniform</name>
		<pose>Unspecified</pose>
		<truncated>0</truncated>
		<difficult>0</difficult>
		<bndbox>
			<xmin>1482</xmin>
			<ymin>825</ymin>
			<xmax>1597</xmax>
			<ymax>1040</ymax>
		</bndbox>
	</object>
	<object>
		<name>Body_without_uniform</name>
		<pose>Unspecified</pose>
		<truncated>0</truncated>
		<difficult>0</difficult>
		<bndbox>
			<xmin>1393</xmin>
			<ymin>785</ymin>
			<xmax>1504</xmax>
			<ymax>1007</ymax>
		</bndbox>
	</object>
</annotation>
